Workbook

Sheet Assumptions
A1: Asset Class | B1: Conservative | C1: Balanced | D1: Growth
A2: US Large-Cap Equities (IVV) | B2: 0.3 | C2: 0.45 | D2: 0.6
A3: International Equities (IXUS) | B3: 0.1 | C3: 0.15 | D3: 0.2
A4: US Treasury Bonds (IEF) | B4: 0.6 | C4: 0.4 | D4: 0.2
A5: Total | B5: =SUM(B2:B4) -> 1 | C5: =SUM(C2:C4) -> 1 | D5: =SUM(D2:D4) -> 1
A8: Rebalancing | B8: Monthly
A9: Transaction costs and taxes | B9: Not included
A10: Initial Investment | B10: 10000
A12: Internal Reference Portfolio | B12: Balanced: 45% IVV / 15% IXUS / 40% IEF

Sheet Data
A1: Date | B1: US Equity Adjusted Close | C1: International Equity Adjusted Close | D1: Treasury Adjusted Close
A2: 42369 | B2: 171.99403 | C2: 36.784359 | D2: 82.27211
A3: 42398 | B3: 163.38887 | C3: 34.717655 | D3: 85.014793
A4: 42429 | B4: 163.29657 | C4: 34.04858 | D4: 86.278153
A5: 42460 | B5: 173.48843 | C5: 36.754623 | D5: 86.221085
A6: 42489 | B6: 174.16846 | C6: 37.654163 | D6: 86.08641
A7: 42521 | B7: 177.11516 | C7: 37.260151 | D7: 86.001
A8: 42551 | B8: 177.5643 | C8: 36.950127 | D8: 88.656418
A9: 42580 | B9: 184.20288 | C9: 38.48217 | D9: 88.874908
A10: 42613 | B10: 184.43909 | C10: 38.708576 | D10: 87.976044
A11: 42643 | B11: 184.45145 | C11: 39.41045 | D11: 88.184898
A12: 42674 | B12: 181.17032 | C12: 38.701027 | D12: 86.86676
A13: 42704 | B13: 187.81726 | C13: 37.818035 | D13: 83.194748
... A122: 46022 | B122: 679.32831 | C122: 83.557075 | D122: 93.329948

Sheet Returns
A1: Date | B1: IVV Return | C1: IXUS Return | D1: IEF Return | F1: Date | G1: RF Monthly | H1: Conservative Excess | I1: Balanced Excess | J1: Growth Excess
A2: =Data!A3 -> 42398 | B2: =Data!B3/Data!B2-1 -> -0.050031759 | C2: =Data!C3/Data!C2-1 -> -0.056184309 | D2: =Data!D3/Data!D2-1 -> 0.033336733 | F2: 42398 | G2: 0.0001 | H2: =Portfolio!B2-$G2 -> -0.00072591846 | I2: =Portfolio!C2-$G2 -> -0.017707244 | J2: =Portfolio!D2-$G2 -> -0.03468857
A3: =Data!A4 -> 42429 | B3: =Data!B4/Data!B3-1 -> -0.00056490996 | C3: =Data!C4/Data!C3-1 -> -0.019271895 | D3: =Data!D4/Data!D3-1 -> 0.014860462 | F3: 42429 | G3: 0.0002 | H3: =Portfolio!B3-$G3 -> 0.0066196147 | I3: =Portfolio!C3-$G3 -> 0.0025991911 | J3: =Portfolio!D3-$G3 -> -0.0014212326
A4: =Data!A5 -> 42460 | B4: =Data!B5/Data!B4-1 -> 0.062413215 | C4: =Data!C5/Data!C4-1 -> 0.079475948 | D4: =Data!D5/Data!D4-1 -> -0.00066144091 | F4: 42460 | G4: 0.0002 | H4: =Portfolio!B4-$G4 -> 0.026074695 | I4: =Portfolio!C4-$G4 -> 0.039542763 | J4: =Portfolio!D4-$G4 -> 0.053010831
A5: =Data!A6 -> 42489 | B5: =Data!B6/Data!B5-1 -> 0.0039197022 | C5: =Data!C6/Data!C5-1 -> 0.0244742 | D5: =Data!D6/Data!D5-1 -> -0.0015619625 | F5: 42489 | G5: 0.0001 | H5: =Portfolio!B5-$G5 -> 0.0025861532 | I5: =Portfolio!C5-$G5 -> 0.004710211 | J5: =Portfolio!D5-$G5 -> 0.0068342688
A6: =Data!A7 -> 42521 | B6: =Data!B7/Data!B6-1 -> 0.016918684 | C6: =Data!C7/Data!C6-1 -> -0.010463982 | D6: =Data!D7/Data!D6-1 -> -0.00099215427 | F6: 42521 | G6: 0.0001 | H6: =Portfolio!B6-$G6 -> 0.0033339143 | I6: =Portfolio!C6-$G6 -> 0.0055469485 | J6: =Portfolio!D6-$G6 -> 0.0077599828
A7: =Data!A8 -> 42551 | B7: =Data!B8/Data!B7-1 -> 0.0025358812 | C7: =Data!C8/Data!C7-1 -> -0.0083205326 | D7: =Data!D8/Data!D7-1 -> 0.030876598 | F7: 42551 | G7: 0.0002 | H7: =Portfolio!B7-$G7 -> 0.01825467 | I7: =Portfolio!C7-$G7 -> 0.012043706 | J7: =Portfolio!D7-$G7 -> 0.0058327418
A8: =Data!A9 -> 42580 | B8: =Data!B9/Data!B8-1 -> 0.037386907 | C8: =Data!C9/Data!C8-1 -> 0.04146247 | D8: =Data!D9/Data!D8-1 -> 0.0024644646 | F8: 42580 | G8: 0.0002 | H8: =Portfolio!B8-$G8 -> 0.016640998 | I8: =Portfolio!C8-$G8 -> 0.023829264 | J8: =Portfolio!D8-$G8 -> 0.031017531
A9: =Data!A10 -> 42613 | B9: =Data!B10/Data!B9-1 -> 0.0012823144 | C9: =Data!C10/Data!C9-1 -> 0.0058834026 | D9: =Data!D10/Data!D9-1 -> -0.010113819 | F9: 42613 | G9: 0.0002 | H9: =Portfolio!B9-$G9 -> -0.0052952566 | I9: =Portfolio!C9-$G9 -> -0.0027859756 | J9: =Portfolio!D9-$G9 -> -0.00027669458
A10: =Data!A11 -> 42643 | B10: =Data!B11/Data!B10-1 -> 6.7013995e-05 | C10: =Data!C11/Data!C10-1 -> 0.018132256 | D10: =Data!D11/Data!D10-1 -> 0.0023739951 | F10: 42643 | G10: 0.0002 | H10: =Portfolio!B10-$G10 -> 0.0030577268 | I10: =Portfolio!C10-$G10 -> 0.0034995927 | J10: =Portfolio!D10-$G10 -> 0.0039414586
A11: =Data!A12 -> 42674 | B11: =Data!B12/Data!B11-1 -> -0.017788573 | C11: =Data!C12/Data!C11-1 -> -0.018000888 | D11: =Data!D12/Data!D11-1 -> -0.014947436 | F11: 42674 | G11: 0.0002 | H11: =Portfolio!B11-$G11 -> -0.016305122 | I11: =Portfolio!C11-$G11 -> -0.016883965 | J11: =Portfolio!D11-$G11 -> -0.017462808
A12: =Data!A13 -> 42704 | B12: =Data!B13/Data!B12-1 -> 0.036688913 | C12: =Data!C13/Data!C12-1 -> -0.02281572 | D12: =Data!D13/Data!D12-1 -> -0.042271778 | F12: 42704 | G12: 0.0001 | H12: =Portfolio!B12-$G12 -> -0.016737965 | I12: =Portfolio!C12-$G12 -> -0.0039210585 | J12: =Portfolio!D12-$G12 -> 0.0088958479
A13: =Data!A14 -> 42734 | B13: =Data!B14/Data!B13-1 -> 0.021433701 | C13: =Data!C14/Data!C13-1 -> 0.018548645 | D13: =Data!D14/Data!D13-1 -> -0.0011850147 | F13: 42734 | G13: 0.0003 | H13: =Portfolio!B13-$G13 -> 0.0072739659 | I13: =Portfolio!C13-$G13 -> 0.011653456 | J13: =Portfolio!D13-$G13 -> 0.016032947
... A121: =Data!A122 -> 46022 | B121: =Data!B122/Data!B121-1 -> 0.00070669074 | C121: =Data!C122/Data!C121-1 -> 0.023378877 | D121: =Data!D122/Data!D121-1 -> -0.0076119671 | F121: 46022 | G121: 0.0034 | H121: =Portfolio!B121-$G121 -> -0.0054172853 | I121: =Portfolio!C121-$G121 -> -0.0026199444 | J121: =Portfolio!D121-$G121 -> 0.00017739653

Sheet Portfolio
A1: Date | B1: Conservative Return | C1: Balanced Return | D1: Growth Return | F1: Date | G1: Conservative Value | H1: Balanced Value | I1: Growth Value | K1: Conservative Peak | L1: Balanced Peak | M1: Growth Peak | O1: Conservative Drawdown | P1: Balanced Drawdown | Q1: Growth Drawdown
A2: =Returns!A2 -> 42398 | B2: =Returns!B2*Assumptions!$B$2+Returns!C2*Assumptions!$B$3+Returns!D2*Assumptions!$B$4 -> -0.00062591846 | C2: =Returns!B2*Assumptions!$C$2+Returns!C2*Assumptions!$C$3+Returns!D2*Assumptions!$C$4 -> -0.017607244 | D2: =Returns!B2*Assumptions!$D$2+Returns!C2*Assumptions!$D$3+Returns!D2*Assumptions!$D$4 -> -0.03458857 | F2: =Data!A2 -> 42369 | G2: =Assumptions!$B$10 -> 10000 | H2: =Assumptions!$B$10 -> 10000 | I2: =Assumptions!$B$10 -> 10000 | K2: =MAX(G$2:G2) -> 10000 | L2: =MAX(H$2:H2) -> 10000 | M2: =MAX(I$2:I2) -> 10000 | O2: =G2/K2-1 -> 0 | P2: =H2/L2-1 -> 0 | Q2: =I2/M2-1 -> 0
A3: =Returns!A3 -> 42429 | B3: =Returns!B3*Assumptions!$B$2+Returns!C3*Assumptions!$B$3+Returns!D3*Assumptions!$B$4 -> 0.0068196147 | C3: =Returns!B3*Assumptions!$C$2+Returns!C3*Assumptions!$C$3+Returns!D3*Assumptions!$C$4 -> 0.0027991911 | D3: =Returns!B3*Assumptions!$D$2+Returns!C3*Assumptions!$D$3+Returns!D3*Assumptions!$D$4 -> -0.0012212326 | F3: =A2 -> 42398 | G3: =G2*(1+B2) -> 9993.7408 | H3: =H2*(1+C2) -> 9823.9276 | I3: =I2*(1+D2) -> 9654.1143 | K3: =MAX(G$2:G3) -> 10000 | L3: =MAX(H$2:H3) -> 10000 | M3: =MAX(I$2:I3) -> 10000 | O3: =G3/K3-1 -> -0.00062591846 | P3: =H3/L3-1 -> -0.017607244 | Q3: =I3/M3-1 -> -0.03458857
A4: =Returns!A4 -> 42460 | B4: =Returns!B4*Assumptions!$B$2+Returns!C4*Assumptions!$B$3+Returns!D4*Assumptions!$B$4 -> 0.026274695 | C4: =Returns!B4*Assumptions!$C$2+Returns!C4*Assumptions!$C$3+Returns!D4*Assumptions!$C$4 -> 0.039742763 | D4: =Returns!B4*Assumptions!$D$2+Returns!C4*Assumptions!$D$3+Returns!D4*Assumptions!$D$4 -> 0.053210831 | F4: =A3 -> 42429 | G4: =G3*(1+B3) -> 10061.894 | H4: =H3*(1+C3) -> 9851.4266 | I4: =I3*(1+D3) -> 9642.3244 | K4: =MAX(G$2:G4) -> 10061.894 | L4: =MAX(H$2:H4) -> 10000 | M4: =MAX(I$2:I4) -> 10000 | O4: =G4/K4-1 -> 0 | P4: =H4/L4-1 -> -0.014857339 | Q4: =I4/M4-1 -> -0.035767562
A5: =Returns!A5 -> 42489 | B5: =Returns!B5*Assumptions!$B$2+Returns!C5*Assumptions!$B$3+Returns!D5*Assumptions!$B$4 -> 0.0026861532 | C5: =Returns!B5*Assumptions!$C$2+Returns!C5*Assumptions!$C$3+Returns!D5*Assumptions!$C$4 -> 0.004810211 | D5: =Returns!B5*Assumptions!$D$2+Returns!C5*Assumptions!$D$3+Returns!D5*Assumptions!$D$4 -> 0.0069342688 | F5: =A4 -> 42460 | G5: =G4*(1+B4) -> 10326.267 | H5: =H4*(1+C4) -> 10242.95 | I5: =I4*(1+D4) -> 10155.4 | K5: =MAX(G$2:G5) -> 10326.267 | L5: =MAX(H$2:H5) -> 10242.95 | M5: =MAX(I$2:I5) -> 10155.4 | O5: =G5/K5-1 -> 0 | P5: =H5/L5-1 -> 0 | Q5: =I5/M5-1 -> 0
A6: =Returns!A6 -> 42521 | B6: =Returns!B6*Assumptions!$B$2+Returns!C6*Assumptions!$B$3+Returns!D6*Assumptions!$B$4 -> 0.0034339143 | C6: =Returns!B6*Assumptions!$C$2+Returns!C6*Assumptions!$C$3+Returns!D6*Assumptions!$C$4 -> 0.0056469485 | D6: =Returns!B6*Assumptions!$D$2+Returns!C6*Assumptions!$D$3+Returns!D6*Assumptions!$D$4 -> 0.0078599828 | F6: =A5 -> 42489 | G6: =G5*(1+B5) -> 10354.005 | H6: =H5*(1+C5) -> 10292.22 | I6: =I5*(1+D5) -> 10225.821 | K6: =MAX(G$2:G6) -> 10354.005 | L6: =MAX(H$2:H6) -> 10292.22 | M6: =MAX(I$2:I6) -> 10225.821 | O6: =G6/K6-1 -> 0 | P6: =H6/L6-1 -> 0 | Q6: =I6/M6-1 -> 0
A7: =Returns!A7 -> 42551 | B7: =Returns!B7*Assumptions!$B$2+Returns!C7*Assumptions!$B$3+Returns!D7*Assumptions!$B$4 -> 0.01845467 | C7: =Returns!B7*Assumptions!$C$2+Returns!C7*Assumptions!$C$3+Returns!D7*Assumptions!$C$4 -> 0.012243706 | D7: =Returns!B7*Assumptions!$D$2+Returns!C7*Assumptions!$D$3+Returns!D7*Assumptions!$D$4 -> 0.0060327418 | F7: =A6 -> 42521 | G7: =G6*(1+B6) -> 10389.56 | H7: =H6*(1+C6) -> 10350.34 | I7: =I6*(1+D6) -> 10306.196 | K7: =MAX(G$2:G7) -> 10389.56 | L7: =MAX(H$2:H7) -> 10350.34 | M7: =MAX(I$2:I7) -> 10306.196 | O7: =G7/K7-1 -> 0 | P7: =H7/L7-1 -> 0 | Q7: =I7/M7-1 -> 0
A8: =Returns!A8 -> 42580 | B8: =Returns!B8*Assumptions!$B$2+Returns!C8*Assumptions!$B$3+Returns!D8*Assumptions!$B$4 -> 0.016840998 | C8: =Returns!B8*Assumptions!$C$2+Returns!C8*Assumptions!$C$3+Returns!D8*Assumptions!$C$4 -> 0.024029264 | D8: =Returns!B8*Assumptions!$D$2+Returns!C8*Assumptions!$D$3+Returns!D8*Assumptions!$D$4 -> 0.031217531 | F8: =A7 -> 42551 | G8: =G7*(1+B7) -> 10581.296 | H8: =H7*(1+C7) -> 10477.066 | I8: =I7*(1+D7) -> 10368.37 | K8: =MAX(G$2:G8) -> 10581.296 | L8: =MAX(H$2:H8) -> 10477.066 | M8: =MAX(I$2:I8) -> 10368.37 | O8: =G8/K8-1 -> 0 | P8: =H8/L8-1 -> 0 | Q8: =I8/M8-1 -> 0
A9: =Returns!A9 -> 42613 | B9: =Returns!B9*Assumptions!$B$2+Returns!C9*Assumptions!$B$3+Returns!D9*Assumptions!$B$4 -> -0.0050952566 | C9: =Returns!B9*Assumptions!$C$2+Returns!C9*Assumptions!$C$3+Returns!D9*Assumptions!$C$4 -> -0.0025859756 | D9: =Returns!B9*Assumptions!$D$2+Returns!C9*Assumptions!$D$3+Returns!D9*Assumptions!$D$4 -> -7.6694577e-05 | F9: =A8 -> 42580 | G9: =G8*(1+B8) -> 10759.496 | H9: =H8*(1+C8) -> 10728.823 | I9: =I8*(1+D8) -> 10692.045 | K9: =MAX(G$2:G9) -> 10759.496 | L9: =MAX(H$2:H9) -> 10728.823 | M9: =MAX(I$2:I9) -> 10692.045 | O9: =G9/K9-1 -> 0 | P9: =H9/L9-1 -> 0 | Q9: =I9/M9-1 -> 0
A10: =Returns!A10 -> 42643 | B10: =Returns!B10*Assumptions!$B$2+Returns!C10*Assumptions!$B$3+Returns!D10*Assumptions!$B$4 -> 0.0032577268 | C10: =Returns!B10*Assumptions!$C$2+Returns!C10*Assumptions!$C$3+Returns!D10*Assumptions!$C$4 -> 0.0036995927 | D10: =Returns!B10*Assumptions!$D$2+Returns!C10*Assumptions!$D$3+Returns!D10*Assumptions!$D$4 -> 0.0041414586 | F10: =A9 -> 42613 | G10: =G9*(1+B9) -> 10704.673 | H10: =H9*(1+C9) -> 10701.078 | I10: =I9*(1+D9) -> 10691.225 | K10: =MAX(G$2:G10) -> 10759.496 | L10: =MAX(H$2:H10) -> 10728.823 | M10: =MAX(I$2:I10) -> 10692.045 | O10: =G10/K10-1 -> -0.0050952566 | P10: =H10/L10-1 -> -0.0025859756 | Q10: =I10/M10-1 -> -7.6694577e-05
A11: =Returns!A11 -> 42674 | B11: =Returns!B11*Assumptions!$B$2+Returns!C11*Assumptions!$B$3+Returns!D11*Assumptions!$B$4 -> -0.016105122 | C11: =Returns!B11*Assumptions!$C$2+Returns!C11*Assumptions!$C$3+Returns!D11*Assumptions!$C$4 -> -0.016683965 | D11: =Returns!B11*Assumptions!$D$2+Returns!C11*Assumptions!$D$3+Returns!D11*Assumptions!$D$4 -> -0.017262808 | F11: =A10 -> 42643 | G11: =G10*(1+B10) -> 10739.546 | H11: =H10*(1+C10) -> 10740.668 | I11: =I10*(1+D10) -> 10735.502 | K11: =MAX(G$2:G11) -> 10759.496 | L11: =MAX(H$2:H11) -> 10740.668 | M11: =MAX(I$2:I11) -> 10735.502 | O11: =G11/K11-1 -> -0.0018541287 | P11: =H11/L11-1 -> 0 | Q11: =I11/M11-1 -> 0
A12: =Returns!A12 -> 42704 | B12: =Returns!B12*Assumptions!$B$2+Returns!C12*Assumptions!$B$3+Returns!D12*Assumptions!$B$4 -> -0.016637965 | C12: =Returns!B12*Assumptions!$C$2+Returns!C12*Assumptions!$C$3+Returns!D12*Assumptions!$C$4 -> -0.0038210585 | D12: =Returns!B12*Assumptions!$D$2+Returns!C12*Assumptions!$D$3+Returns!D12*Assumptions!$D$4 -> 0.0089958479 | F12: =A11 -> 42674 | G12: =G11*(1+B11) -> 10566.584 | H12: =H11*(1+C11) -> 10561.471 | I12: =I11*(1+D11) -> 10550.177 | K12: =MAX(G$2:G12) -> 10759.496 | L12: =MAX(H$2:H12) -> 10740.668 | M12: =MAX(I$2:I12) -> 10735.502 | O12: =G12/K12-1 -> -0.01792939 | P12: =H12/L12-1 -> -0.016683965 | Q12: =I12/M12-1 -> -0.017262808
A13: =Returns!A13 -> 42734 | B13: =Returns!B13*Assumptions!$B$2+Returns!C13*Assumptions!$B$3+Returns!D13*Assumptions!$B$4 -> 0.0075739659 | C13: =Returns!B13*Assumptions!$C$2+Returns!C13*Assumptions!$C$3+Returns!D13*Assumptions!$C$4 -> 0.011953456 | D13: =Returns!B13*Assumptions!$D$2+Returns!C13*Assumptions!$D$3+Returns!D13*Assumptions!$D$4 -> 0.016332947 | F13: =A12 -> 42704 | G13: =G12*(1+B12) -> 10390.778 | H13: =H12*(1+C12) -> 10521.115 | I13: =I12*(1+D12) -> 10645.085 | K13: =MAX(G$2:G13) -> 10759.496 | L13: =MAX(H$2:H13) -> 10740.668 | M13: =MAX(I$2:I13) -> 10735.502 | O13: =G13/K13-1 -> -0.034269046 | P13: =H13/L13-1 -> -0.020441273 | Q13: =I13/M13-1 -> -0.0084222541
A14: =Returns!A14 -> 42766 | B14: =Returns!B14*Assumptions!$B$2+Returns!C14*Assumptions!$B$3+Returns!D14*Assumptions!$B$4 -> 0.010670229 | C14: =Returns!B14*Assumptions!$C$2+Returns!C14*Assumptions!$C$3+Returns!D14*Assumptions!$C$4 -> 0.014907936 | D14: =Returns!B14*Assumptions!$D$2+Returns!C14*Assumptions!$D$3+Returns!D14*Assumptions!$D$4 -> 0.019145644 | F14: =A13 -> 42734 | G14: =G13*(1+B13) -> 10469.477 | H14: =H13*(1+C13) -> 10646.879 | I14: =I13*(1+D13) -> 10818.951 | K14: =MAX(G$2:G14) -> 10759.496 | L14: =MAX(H$2:H14) -> 10740.668 | M14: =MAX(I$2:I14) -> 10818.951 | O14: =G14/K14-1 -> -0.026954633 | P14: =H14/L14-1 -> -0.008732161 | Q14: =I14/M14-1 -> 0
... A121: =Returns!A121 -> 46022 | B121: =Returns!B121*Assumptions!$B$2+Returns!C121*Assumptions!$B$3+Returns!D121*Assumptions!$B$4 -> -0.0020172853 | C121: =Returns!B121*Assumptions!$C$2+Returns!C121*Assumptions!$C$3+Returns!D121*Assumptions!$C$4 -> 0.00078005563 | D121: =Returns!B121*Assumptions!$D$2+Returns!C121*Assumptions!$D$3+Returns!D121*Assumptions!$D$4 -> 0.0035773965 | F121: =A120 -> 45989 | G121: =G120*(1+B120) -> 18261.978 | H121: =H120*(1+C120) -> 22764.907 | I121: =I120*(1+D120) -> 28115.621 | K121: =MAX(G$2:G121) -> 18261.978 | L121: =MAX(H$2:H121) -> 22764.907 | M121: =MAX(I$2:I121) -> 28115.621 | O121: =G121/K121-1 -> 0 | P121: =H121/L121-1 -> 0 | Q121: =I121/M121-1 -> 0
F122: =A121 -> 46022 | G122: =G121*(1+B121) -> 18225.139 | H122: =H121*(1+C121) -> 22782.665 | I122: =I121*(1+D121) -> 28216.202 | K122: =MAX(G$2:G122) -> 18261.978 | L122: =MAX(H$2:H122) -> 22782.665 | M122: =MAX(I$2:I122) -> 28216.202 | O122: =G122/K122-1 -> -0.0020172853 | P122: =H122/L122-1 -> 0 | Q122: =I122/M122-1 -> 0

Sheet Risk Metrics
A1: Metric | B1: Conservative | C1: Balanced | D1: Growth
A2: Initial Investment | B2: =Portfolio!G2 -> 10000 | C2: =Portfolio!H2 -> 10000 | D2: =Portfolio!I2 -> 10000
A3: Ending Value | B3: =Portfolio!G122 -> 18225.139 | C3: =Portfolio!H122 -> 22782.665 | D3: =Portfolio!I122 -> 28216.202
A4: Total Return | B4: =B3/B2-1 -> 0.82251385 | C4: =C3/C2-1 -> 1.2782665 | D4: =D3/D2-1 -> 1.8216202
A5: Annualized Return (CAGR) | B5: =(B3/B2)^(12/B8)-1 -> 0.061859566 | C5: =(C3/C2)^(12/C8)-1 -> 0.08582654 | D5: =(D3/D2)^(12/D8)-1 -> 0.10930215
A6: Annualized Volatility | B6: =_xlfn.STDEV.S(Portfolio!B2:B121)*SQRT(12) -> 0.075748066 | C6: =_xlfn.STDEV.S(Portfolio!C2:C121)*SQRT(12) -> 0.095344714 | D6: =_xlfn.STDEV.S(Portfolio!D2:D121)*SQRT(12) -> 0.11925864
A7: Maximum Drawdown (Month-End) | B7: =MIN(Portfolio!O2:O122) -> -0.19213748 | C7: =MIN(Portfolio!P2:P122) -> -0.21027444 | D7: =MIN(Portfolio!Q2:Q122) -> -0.22858548
A8: Months of Data | B8: =COUNT(Portfolio!B2:B121) -> 120 | C8: =COUNT(Portfolio!C2:C121) -> 120 | D8: =COUNT(Portfolio!D2:D121) -> 120
A9: Annualized Sharpe Ratio | B9: =AVERAGE(Returns!H2:H121)/_xlfn.STDEV.S(Returns!H2:H121)*SQRT(12) -> 0.55781778 | C9: =AVERAGE(Returns!I2:I121)/_xlfn.STDEV.S(Returns!I2:I121)*SQRT(12) -> 0.69595166 | D9: =AVERAGE(Returns!J2:J121)/_xlfn.STDEV.S(Returns!J2:J121)*SQRT(12) -> 0.75839741
A12: Asset Correlation | B12: IVV | C12: IXUS | D12: IEF
A13: IVV | B13: =CORREL(Returns!$B$2:$B$121,Returns!$B$2:$B$121) -> 1 | C13: =CORREL(Returns!$B$2:$B$121,Returns!$C$2:$C$121) -> 0.84416821 | D13: =CORREL(Returns!$B$2:$B$121,Returns!$D$2:$D$121) -> 0.14854351
A14: IXUS | B14: =CORREL(Returns!$C$2:$C$121,Returns!$B$2:$B$121) -> 0.84416821 | C14: =CORREL(Returns!$C$2:$C$121,Returns!$C$2:$C$121) -> 1 | D14: =CORREL(Returns!$C$2:$C$121,Returns!$D$2:$D$121) -> 0.21517736
A15: IEF | B15: =CORREL(Returns!$D$2:$D$121,Returns!$B$2:$B$121) -> 0.14854351 | C15: =CORREL(Returns!$D$2:$D$121,Returns!$C$2:$C$121) -> 0.21517736 | D15: =CORREL(Returns!$D$2:$D$121,Returns!$D$2:$D$121) -> 1
A18: Difference vs Balanced | B18: Conservative | C18: Growth
A19: Ending Value Difference ($) | B19: =B3-$C$3 -> -4557.5265 | C19: =D3-$C$3 -> 5433.5371
A20: CAGR Difference (pp) | B20: =(B5-$C$5)*100 -> -2.3966974 | C20: =(D5-$C$5)*100 -> 2.3475613
A21: Volatility Difference (pp) | B21: =(B6-$C$6)*100 -> -1.9596649 | C21: =(D6-$C$6)*100 -> 2.3913926
A22: Max Drawdown Magnitude Difference (pp) | B22: =(ABS(B7)-ABS($C$7))*100 -> -1.8136963 | C22: =(ABS(D7)-ABS($C$7))*100 -> 1.8311034
A23: Sharpe Ratio Difference | B23: =B9-$C$9 -> -0.13813388 | C23: =D9-$C$9 -> 0.062445753
A25: pp = percentage points. Differences are calculated using unrounded values.
A26: Annualized Sharpe ratio = mean monthly excess return / standard deviation of monthly excess returns × √12.

Sheet Dashboard
A1: Investment Portfolio & Risk Analysis | K1: Date | L1: Conservative | M1: Balanced | N1: Growth
A2: 2016–2025 | Monthly Rebalancing | Initial Investment: $10,000 | K2: =Portfolio!F2 -> 42369 | L2: =Portfolio!O2 -> 0 | M2: =Portfolio!P2 -> 0 | N2: =Portfolio!Q2 -> 0
K3: =Portfolio!F3 -> 42398 | L3: =Portfolio!O3 -> -0.00062591846 | M3: =Portfolio!P3 -> -0.017607244 | N3: =Portfolio!Q3 -> -0.03458857
A4: Metric | B4: Conservative | C4: Balanced | D4: Growth | K4: =Portfolio!F4 -> 42429 | L4: =Portfolio!O4 -> 0 | M4: =Portfolio!P4 -> -0.014857339 | N4: =Portfolio!Q4 -> -0.035767562
A5: Ending Value | B5: ='Risk Metrics'!B3 -> 18225.139 | C5: ='Risk Metrics'!C3 -> 22782.665 | D5: ='Risk Metrics'!D3 -> 28216.202 | K5: =Portfolio!F5 -> 42460 | L5: =Portfolio!O5 -> 0 | M5: =Portfolio!P5 -> 0 | N5: =Portfolio!Q5 -> 0
A6: Annualized Return (CAGR) | B6: ='Risk Metrics'!B5 -> 0.061859566 | C6: ='Risk Metrics'!C5 -> 0.08582654 | D6: ='Risk Metrics'!D5 -> 0.10930215 | K6: =Portfolio!F6 -> 42489 | L6: =Portfolio!O6 -> 0 | M6: =Portfolio!P6 -> 0 | N6: =Portfolio!Q6 -> 0
A7: Annualized Volatility | B7: ='Risk Metrics'!B6 -> 0.075748066 | C7: ='Risk Metrics'!C6 -> 0.095344714 | D7: ='Risk Metrics'!D6 -> 0.11925864 | K7: =Portfolio!F7 -> 42521 | L7: =Portfolio!O7 -> 0 | M7: =Portfolio!P7 -> 0 | N7: =Portfolio!Q7 -> 0
A8: Maximum Drawdown (Month-End) | B8: ='Risk Metrics'!B7 -> -0.19213748 | C8: ='Risk Metrics'!C7 -> -0.21027444 | D8: ='Risk Metrics'!D7 -> -0.22858548 | K8: =Portfolio!F8 -> 42551 | L8: =Portfolio!O8 -> 0 | M8: =Portfolio!P8 -> 0 | N8: =Portfolio!Q8 -> 0
A9: Annualized Sharpe Ratio | B9: ='Risk Metrics'!B9 -> 0.55781778 | C9: ='Risk Metrics'!C9 -> 0.69595166 | D9: ='Risk Metrics'!D9 -> 0.75839741 | K9: =Portfolio!F9 -> 42580 | L9: =Portfolio!O9 -> 0 | M9: =Portfolio!P9 -> 0 | N9: =Portfolio!Q9 -> 0
K10: =Portfolio!F10 -> 42613 | L10: =Portfolio!O10 -> -0.0050952566 | M10: =Portfolio!P10 -> -0.0025859756 | N10: =Portfolio!Q10 -> -7.6694577e-05
A11: Allocations (IVV / IXUS / IEF): Conservative 30%/10%/60%; Balanced 45%/15%/40%; Growth 60%/20%/20%. | K11: =Portfolio!F11 -> 42643 | L11: =Portfolio!O11 -> -0.0018541287 | M11: =Portfolio!P11 -> 0 | N11: =Portfolio!Q11 -> 0
A12: Historical simulation; monthly rebalancing; excludes trading costs and taxes. Drawdowns use month-end values. | K12: =Portfolio!F12 -> 42674 | L12: =Portfolio!O12 -> -0.01792939 | M12: =Portfolio!P12 -> -0.016683965 | N12: =Portfolio!Q12 -> -0.017262808
K13: =Portfolio!F13 -> 42704 | L13: =Portfolio!O13 -> -0.034269046 | M13: =Portfolio!P13 -> -0.020441273 | N13: =Portfolio!Q13 -> -0.0084222541
K14: =Portfolio!F14 -> 42734 | L14: =Portfolio!O14 -> -0.026954633 | M14: =Portfolio!P14 -> -0.008732161 | N14: =Portfolio!Q14 -> 0
K15: =Portfolio!F15 -> 42766 | L15: =Portfolio!O15 -> -0.016572016 | M15: =Portfolio!P15 -> 0 | N15: =Portfolio!Q15 -> 0
K16: =Portfolio!F16 -> 42794 | L16: =Portfolio!O16 -> 0 | M16: =Portfolio!P16 -> 0 | N16: =Portfolio!Q16 -> 0
K17: =Portfolio!F17 -> 42825 | L17: =Portfolio!O17 -> 0 | M17: =Portfolio!P17 -> 0 | N17: =Portfolio!Q17 -> 0
K18: =Portfolio!F18 -> 42853 | L18: =Portfolio!O18 -> 0 | M18: =Portfolio!P18 -> 0 | N18: =Portfolio!Q18 -> 0
K19: =Portfolio!F19 -> 42886 | L19: =Portfolio!O19 -> 0 | M19: =Portfolio!P19 -> 0 | N19: =Portfolio!Q19 -> 0
K20: =Portfolio!F20 -> 42916 | L20: =Portfolio!O20 -> -0.00023007112 | M20: =Portfolio!P20 -> 0 | N20: =Portfolio!Q20 -> 0
K21: =Portfolio!F21 -> 42947 | L21: =Portfolio!O21 -> 0 | M21: =Portfolio!P21 -> 0 | N21: =Portfolio!Q21 -> 0
K22: =Portfolio!F22 -> 42978 | L22: =Portfolio!O22 -> 0 | M22: =Portfolio!P22 -> 0 | N22: =Portfolio!Q22 -> 0
K23: =Portfolio!F23 -> 43007 | L23: =Portfolio!O23 -> -0.00056864815 | M23: =Portfolio!P23 -> 0 | N23: =Portfolio!Q23 -> 0
K24: =Portfolio!F24 -> 43039 | L24: =Portfolio!O24 -> 0 | M24: =Portfolio!P24 -> 0 | N24: =Portfolio!Q24 -> 0
... K122: =Portfolio!F122 -> 46022 | L122: =Portfolio!O122 -> -0.0020172853 | M122: =Portfolio!P122 -> 0 | N122: =Portfolio!Q122 -> 0
